[{"id":"768bceac.aed6e","type":"tab","label":"Flow 2","disabled":false,"info":""},{"id":"e88a12ef.199c2","type":"ui_switch","z":"768bceac.aed6e","name":"","label":"Fan","tooltip":"","group":"1561bc9b.e559d3","order":3,"width":0,"height":0,"passthru":true,"decouple":"false","topic":"","style":"","onvalue":"1","onvalueType":"num","onicon":"","oncolor":"","offvalue":"0","offvalueType":"num","officon":"","offcolor":"","x":885,"y":109,"wires":[["15cead18.88ae23","a9793b3d.383228"]]},{"id":"15cead18.88ae23","type":"rpi-gpio out","z":"768bceac.aed6e","name":"","pin":"16","set":"","level":"0","freq":"","out":"out","x":1075,"y":109,"wires":[]},{"id":"c85f6e6a.6efef","type":"ui_switch","z":"768bceac.aed6e","name":"","label":"Blue_Light","tooltip":"","group":"1561bc9b.e559d3","order":2,"width":0,"height":0,"passthru":true,"decouple":"false","topic":"","style":"","onvalue":"1","onvalueType":"num","onicon":"","oncolor":"","offvalue":"0","offvalueType":"num","officon":"","offcolor":"","x":890,"y":380,"wires":[["b874b0cc.11c5e","a741611.2f3faa"]]},{"id":"b874b0cc.11c5e","type":"rpi-gpio out","z":"768bceac.aed6e","name":"","pin":"31","set":"","level":"0","freq":"","out":"out","x":1060,"y":380,"wires":[]},{"id":"a710adbf.e2ae9","type":"ui_text","z":"768bceac.aed6e","group":"76c72daa.8ac404","order":0,"width":0,"height":0,"name":"","label":"Motion_Alert","format":"{{msg.payload}}","layout":"row-spread","x":490,"y":440,"wires":[]},{"id":"6cecdbac.de9844","type":"ui_switch","z":"768bceac.aed6e","name":"","label":"Exhaust_Fan","tooltip":"","group":"7bc51687.4e2538","order":1,"width":0,"height":0,"passthru":true,"decouple":"false","topic":"","style":"","onvalue":"1","onvalueType":"num","onicon":"","oncolor":"","offvalue":"0","offvalueType":"num","officon":"","offcolor":"","x":890,"y":220,"wires":[["ce77280b.4800c8","ab11f5d6.b50dc8"]]},{"id":"ce77280b.4800c8","type":"rpi-gpio out","z":"768bceac.aed6e","name":"","pin":"18","set":"","level":"0","freq":"","out":"out","x":1060,"y":220,"wires":[]},{"id":"daf7c8f0.fddc88","type":"rpi-gpio in","z":"768bceac.aed6e","name":"","pin":"13","intype":"tri","debounce":"25","read":false,"x":70,"y":280,"wires":[["97db2107.1fbbf"]]},{"id":"97db2107.1fbbf","type":"function","z":"768bceac.aed6e","name":"Fiame Sensor","func":"\n //var msg1;\nif (msg.payload === 0){\n    msg.payload =1;\n    msg.payload= Number(msg.payload);\n    return msg;\n}\nif( msg.payload === 1){\n    msg.payload = 0;\n     msg.payload= Number(msg.payload);\nreturn msg;\n}\n  ","outputs":1,"noerr":0,"x":200,"y":320,"wires":[["b637bac.a016348","8e632bf3.18f308"]]},{"id":"91419bb9.496858","type":"debug","z":"768bceac.aed6e","name":"","active":true,"tosidebar":true,"console":false,"tostatus":false,"complete":"true","targetType":"full","x":330,"y":856,"wires":[]},{"id":"1db200f.81588ff","type":"ui_gauge","z":"768bceac.aed6e","name":"","group":"33731033.34ef4","order":1,"width":0,"height":0,"gtype":"gage","title":"gauge","label":"'C","format":"{{value}}","min":"0","max":"50","colors":["#00b500","#e6e600","#ca3838"],"seg1":"","seg2":"","x":250,"y":816,"wires":[]},{"id":"956f640c.55c078","type":"switch","z":"768bceac.aed6e","name":"Change","property":"switch","propertyType":"flow","rules":[{"t":"eq","v":"1","vt":"num"}],"checkall":"false","repair":false,"outputs":1,"x":100,"y":474,"wires":[["fec473a1.18218","f550f846.1cd6f8","a710adbf.e2ae9","7bf321d0.f1c82"]]},{"id":"bb20725f.6dd7d","type":"change","z":"768bceac.aed6e","name":"switch","rules":[{"t":"set","p":"switch","pt":"flow","to":"payload","tot":"msg"}],"action":"","property":"","from":"","to":"","reg":false,"x":407,"y":710,"wires":[["7d1b8540.30565c"]]},{"id":"fec473a1.18218","type":"debug","z":"768bceac.aed6e","name":"","active":true,"tosidebar":true,"console":false,"tostatus":false,"complete":"PIR","targetType":"msg","x":280,"y":480,"wires":[]},{"id":"f929ef79.a26ea","type":"inject","z":"768bceac.aed6e","name":"","topic":"","payload":"1","payloadType":"num","repeat":"","crontab":"","once":false,"onceDelay":0.1,"x":97,"y":670,"wires":[["9c83c48f.72b898"]]},{"id":"222dd84c.5e60d8","type":"inject","z":"768bceac.aed6e","name":"","topic":"","payload":"0","payloadType":"num","repeat":"","crontab":"","once":false,"onceDelay":0.1,"x":97,"y":730,"wires":[["9c83c48f.72b898"]]},{"id":"9c83c48f.72b898","type":"ui_switch","z":"768bceac.aed6e","name":"","label":"switch","tooltip":"","group":"a5d70956.dca588","order":5,"width":0,"height":0,"passthru":true,"decouple":"false","topic":"switch","style":"","onvalue":"1","onvalueType":"num","onicon":"","oncolor":"","offvalue":"0","offvalueType":"num","officon":"","offcolor":"","x":257,"y":710,"wires":[["bb20725f.6dd7d"]]},{"id":"bd7cf6b.e741e08","type":"e-mail","z":"768bceac.aed6e","server":"smtp.gmail.com","port":"465","secure":true,"tls":true,"name":"","dname":"Email","x":690,"y":576,"wires":[]},{"id":"96b67804.2dba18","type":"function","z":"768bceac.aed6e","name":"Source","func":"msg.payload={};\nmsg.payload.type=\"photo\";\nmsg.payload.caption=\"Next photo in sequence\";\nmsg.payload.content=\"/var/lib/motion/lastsnap.jpg\";\nreturn msg;","outputs":1,"noerr":0,"x":400,"y":516,"wires":[["27e7bd75.e4a152"]]},{"id":"27e7bd75.e4a152","type":"file in","z":"768bceac.aed6e","name":".jpg file path","filename":"/var/lib/motion/lastsnap.jpg","format":"","chunk":false,"sendError":false,"x":430,"y":580,"wires":[["11c2a342.14ba7d"]]},{"id":"11c2a342.14ba7d","type":"change","z":"768bceac.aed6e","name":"attach","rules":[{"t":"set","p":"attachments","pt":"msg","to":"payload","tot":"msg"}],"action":"","property":"","from":"","to":"","reg":false,"x":570,"y":536,"wires":[["bd7cf6b.e741e08"]]},{"id":"c79b23e3.b4b26","type":"comment","z":"768bceac.aed6e","name":"If motion detection, then send Picture to email","info":"","x":175,"y":362,"wires":[]},{"id":"f550f846.1cd6f8","type":"http request","z":"768bceac.aed6e","name":"Snapshot","method":"GET","ret":"txt","paytoqs":false,"url":"http://192.168.178.50:8080/0/action/snapshot","tls":"","persist":false,"proxy":"","authType":"","x":260,"y":556,"wires":[["96b67804.2dba18"]]},{"id":"ef5dd7bb.3ccca8","type":"inject","z":"768bceac.aed6e","name":"","topic":"","payload":"true","payloadType":"bool","repeat":"","crontab":"","once":false,"onceDelay":0.1,"x":110,"y":582,"wires":[["f550f846.1cd6f8"]]},{"id":"5156ee97.6641b","type":"comment","z":"768bceac.aed6e","name":"Just a live view of cameras","info":"","x":110,"y":20,"wires":[]},{"id":"4ee02de2.87b784","type":"ui_template","z":"768bceac.aed6e","group":"d554621.98026a","name":"Just a view of cameras","order":1,"width":"7","height":"5","format":"<!DOCTYPE html>\n<html>\n<style>\nimg {\n    border: 1px solid #ddd;\n    border-radius: 8px;\n    padding: 2px;\n    width: 320px;\n}\n</style>\n\n<script type=\"text/javascript\">\nscope.$watch('msg', function(msg) {\n    inMessage(msg.payload);\n});\n\nfunction selectCam(url) {\n    document.getElementById('cX').src = url;\n}\n\nfunction inMessage(event) {\n    if (event.match('http://')) {\n        selectCam(event);\n    }\n}\n\n</script>\n<center>\n<table>\n    <tr><!-- Row 1 -->\n    \t\t<td style=\"text-align: center\"><img src=\"\" id=\"cX\" /></td>\n    </tr>\n</table>\n</center>\n</html>","storeOutMessages":false,"fwdInMessages":false,"templateScope":"local","x":340,"y":60,"wires":[[]]},{"id":"ac2d6167.8b2e5","type":"inject","z":"768bceac.aed6e","name":"","topic":"","payload":"http://192.168.178.50:8081","payloadType":"str","repeat":"","crontab":"","once":false,"onceDelay":0.1,"x":100,"y":60,"wires":[["4ee02de2.87b784"]]},{"id":"7d1b8540.30565c","type":"ui_text","z":"768bceac.aed6e","group":"a5d70956.dca588","order":1,"width":0,"height":0,"name":"Security","label":"Security Activation Status","format":"{{msg.payload}}=NO","layout":"row-spread","x":547,"y":710,"wires":[]},{"id":"e9fd1e71.ad283","type":"comment","z":"768bceac.aed6e","name":"Security Switch","info":"","x":87,"y":630,"wires":[]},{"id":"3931195c.765f96","type":"comment","z":"768bceac.aed6e","name":"Temperature At GPIO4 1_Wire","info":"","x":120,"y":776,"wires":[]},{"id":"d4fa8608.98d808","type":"comment","z":"768bceac.aed6e","name":"RFID Door Open/Close","info":"","x":105,"y":899,"wires":[]},{"id":"a69b3896.fb06e8","type":"rpi-gpio out","z":"768bceac.aed6e","name":"Servo 15","pin":"15","set":"","level":"0","freq":"100","out":"pwm","x":540,"y":1036,"wires":[]},{"id":"e2333920.c34a08","type":"inject","z":"768bceac.aed6e","name":"Motor Stop","topic":"","payload":"0","payloadType":"num","repeat":"4","crontab":"","once":false,"onceDelay":"","x":270,"y":1036,"wires":[["a69b3896.fb06e8"]]},{"id":"b183ddea.a6788","type":"daemon","z":"768bceac.aed6e","name":"RFIDReader","command":"python","args":"-u /home/pi/rfidreader.py","autorun":true,"cr":true,"redo":true,"op":"string","x":90,"y":950,"wires":[["8713f9a9.bf5528"],[],[]]},{"id":"8713f9a9.bf5528","type":"function","z":"768bceac.aed6e","name":"Assign Payload","func":"//msg.payload = JSON.parse(msg.payload);\nif (msg.payload == \"Card detected\\n\")\n{\nmsg.payload = 1;\n}\n//else {\n//msg.payload = 1;\n//}\nreturn msg;","outputs":1,"noerr":0,"x":260,"y":956,"wires":[["3380800a.edfdc","5e4e41d6.5c762"]]},{"id":"3380800a.edfdc","type":"debug","z":"768bceac.aed6e","name":"","active":true,"tosidebar":true,"console":true,"tostatus":false,"complete":"true","targetType":"full","x":430,"y":956,"wires":[]},{"id":"5e4e41d6.5c762","type":"trigger","z":"768bceac.aed6e","op1":"3","op2":"15","op1type":"num","op2type":"num","duration":"8","extend":false,"units":"s","reset":"","bytopic":"all","name":"Open for 8s","x":410,"y":996,"wires":[["a69b3896.fb06e8"]]},{"id":"80f8e9da.eb44f8","type":"comment","z":"768bceac.aed6e","name":"Smoke Sensor","info":"","x":95,"y":121,"wires":[]},{"id":"b637bac.a016348","type":"ui_text","z":"768bceac.aed6e","group":"76c72daa.8ac404","order":1,"width":0,"height":0,"name":"","label":"Fire_Alert","format":"{{msg.payload}}","layout":"row-spread","x":340,"y":280,"wires":[]},{"id":"25cc355d.89f98a","type":"rpi-gpio in","z":"768bceac.aed6e","name":"","pin":"5","intype":"tri","debounce":"25","read":false,"x":70,"y":180,"wires":[["8a596b4a.620c58"]]},{"id":"8a596b4a.620c58","type":"function","z":"768bceac.aed6e","name":"Smoke Sensor","func":"\n //var msg1;\nif (msg.payload === 0){\n    msg.payload =1;\n    msg.payload= Number(msg.payload);\n    return msg;\n}\nif( msg.payload === 1){\n    msg.payload = 0;\n     msg.payload= Number(msg.payload);\nreturn msg;\n}\n  ","outputs":1,"noerr":0,"x":220,"y":191,"wires":[["a85538d9.cb1f28","b45736fe.4c2c78"]]},{"id":"4eb58bc2.f24ee4","type":"comment","z":"768bceac.aed6e","name":"Fire Sensor","info":"","x":85,"y":241,"wires":[]},{"id":"a85538d9.cb1f28","type":"ui_text","z":"768bceac.aed6e","group":"76c72daa.8ac404","order":2,"width":0,"height":0,"name":"","label":"Smoke_Alert","format":"{{msg.payload}}","layout":"row-spread","x":410,"y":160,"wires":[]},{"id":"67268f04.2577f","type":"ui_switch","z":"768bceac.aed6e","name":"","label":"Main_Light","tooltip":"","group":"528e8223.243eec","order":0,"width":0,"height":0,"passthru":true,"decouple":"false","topic":"","style":"","onvalue":"1","onvalueType":"num","onicon":"","oncolor":"","offvalue":"0","offvalueType":"num","officon":"","offcolor":"","x":895,"y":480,"wires":[["e3166a58.e85dd8","b87d7a32.791508"]]},{"id":"e3166a58.e85dd8","type":"rpi-gpio out","z":"768bceac.aed6e","name":"","pin":"33","set":"","level":"0","freq":"","out":"out","x":1065,"y":480,"wires":[]},{"id":"560201a5.0f4bb","type":"ui_switch","z":"768bceac.aed6e","name":"","label":"Orange_Light","tooltip":"","group":"7bc51687.4e2538","order":0,"width":0,"height":0,"passthru":true,"decouple":"false","topic":"","style":"","onvalue":"1","onvalueType":"num","onicon":"","oncolor":"","offvalue":"0","offvalueType":"num","officon":"","offcolor":"","x":905,"y":577,"wires":[["6d8b568.922f4a8","d4c808cd.adb378"]]},{"id":"6d8b568.922f4a8","type":"rpi-gpio out","z":"768bceac.aed6e","name":"","pin":"37","set":"","level":"0","freq":"","out":"out","x":1065,"y":577,"wires":[]},{"id":"dc2b031a.07146","type":"ui_switch","z":"768bceac.aed6e","name":"","label":"Green_Light","tooltip":"","group":"a924f6c.a36d908","order":0,"width":0,"height":0,"passthru":true,"decouple":"false","topic":"","style":"","onvalue":"1","onvalueType":"num","onicon":"","oncolor":"","offvalue":"0","offvalueType":"num","officon":"","offcolor":"","x":895,"y":669,"wires":[["b9aaacc6.f9453","ec995500.6b89c8"]]},{"id":"b9aaacc6.f9453","type":"rpi-gpio out","z":"768bceac.aed6e","name":"","pin":"35","set":"","level":"0","freq":"","out":"out","x":1065,"y":669,"wires":[]},{"id":"2fc86c95.641ad4","type":"ui_switch","z":"768bceac.aed6e","name":"","label":"Door_Light","tooltip":"","group":"528e8223.243eec","order":1,"width":0,"height":0,"passthru":true,"decouple":"false","topic":"","style":"","onvalue":"1","onvalueType":"num","onicon":"","oncolor":"","offvalue":"0","offvalueType":"num","officon":"","offcolor":"","x":895,"y":754,"wires":[["d0105a8d.159368","665cf0bc.b505d"]]},{"id":"d0105a8d.159368","type":"rpi-gpio out","z":"768bceac.aed6e","name":"","pin":"36","set":"","level":"0","freq":"","out":"out","x":1065,"y":754,"wires":[]},{"id":"9d6112c5.d554f","type":"rpi-gpio out","z":"768bceac.aed6e","name":"","pin":"38","set":"","level":"0","freq":"","out":"out","x":1065,"y":836,"wires":[]},{"id":"b5b6b3f1.da039","type":"comment","z":"768bceac.aed6e","name":"Light Switch","info":"","x":845,"y":304,"wires":[]},{"id":"f6c0b9bc.3758d8","type":"comment","z":"768bceac.aed6e","name":"Fan Switch","info":"","x":835,"y":20,"wires":[]},{"id":"a9721fd4.5ef61","type":"comment","z":"768bceac.aed6e","name":"SDA\t24, SCK 23, MOSI 19, MISO 21, RST 22, IRQ Nil","info":"","x":420,"y":904,"wires":[]},{"id":"601e547f.f99d6c","type":"rpi-gpio in","z":"768bceac.aed6e","name":"","pin":"29","intype":"tri","debounce":"25","read":false,"x":70,"y":420,"wires":[["956f640c.55c078"]]},{"id":"59b40d22.569034","type":"rpi-gpio out","z":"768bceac.aed6e","name":"Buzzer","pin":"11","set":"","level":"0","freq":"","out":"out","x":610,"y":380,"wires":[]},{"id":"71ef1c91.18c2f4","type":"sensor-ds18b20","z":"768bceac.aed6e","name":"Temp.","topic":"","sensorid":"10-0008039f1ac1","timer":"20","repeat":true,"x":90,"y":840,"wires":[["1db200f.81588ff","91419bb9.496858"]]},{"id":"ada2fd0c.464e1","type":"play audio","z":"768bceac.aed6e","name":"High Alert","voice":"0","x":620,"y":200,"wires":[]},{"id":"de511404.5ae608","type":"file in","z":"768bceac.aed6e","name":".pm3 file path","filename":"/home/pi/Desktop/alert.mp3","format":"","chunk":false,"sendError":false,"x":560,"y":260,"wires":[["ada2fd0c.464e1"]]},{"id":"e958e135.6d0b","type":"inject","z":"768bceac.aed6e","name":"Buzzer stop","topic":"","payload":"0","payloadType":"num","repeat":"","crontab":"","once":false,"onceDelay":0.1,"x":590,"y":320,"wires":[["59b40d22.569034"]]},{"id":"a9793b3d.383228","type":"change","z":"768bceac.aed6e","name":"switch","rules":[{"t":"set","p":"switchfan","pt":"flow","to":"payload","tot":"msg"}],"action":"","property":"","from":"","to":"","reg":false,"x":1023,"y":69,"wires":[[]]},{"id":"ab11f5d6.b50dc8","type":"change","z":"768bceac.aed6e","name":"switch","rules":[{"t":"set","p":"switchexhaustfan","pt":"flow","to":"payload","tot":"msg"}],"action":"","property":"","from":"","to":"","reg":false,"x":1030,"y":180,"wires":[[]]},{"id":"a741611.2f3faa","type":"change","z":"768bceac.aed6e","name":"switch","rules":[{"t":"set","p":"switchblue","pt":"flow","to":"payload","tot":"msg"}],"action":"","property":"","from":"","to":"","reg":false,"x":1025,"y":340,"wires":[[]]},{"id":"b87d7a32.791508","type":"change","z":"768bceac.aed6e","name":"switch","rules":[{"t":"set","p":"switchmain","pt":"flow","to":"payload","tot":"msg"}],"action":"","property":"","from":"","to":"","reg":false,"x":1029,"y":437,"wires":[[]]},{"id":"d4c808cd.adb378","type":"change","z":"768bceac.aed6e","name":"switch","rules":[{"t":"set","p":"switchorange","pt":"flow","to":"payload","tot":"msg"}],"action":"","property":"","from":"","to":"","reg":false,"x":1042,"y":533,"wires":[[]]},{"id":"ec995500.6b89c8","type":"change","z":"768bceac.aed6e","name":"switch","rules":[{"t":"set","p":"switchgreen","pt":"flow","to":"payload","tot":"msg"}],"action":"","property":"","from":"","to":"","reg":false,"x":1029,"y":625,"wires":[[]]},{"id":"665cf0bc.b505d","type":"change","z":"768bceac.aed6e","name":"switch","rules":[{"t":"set","p":"switchdoor","pt":"flow","to":"payload","tot":"msg"}],"action":"","property":"","from":"","to":"","reg":false,"x":1029,"y":713,"wires":[[]]},{"id":"b526accf.0b9e9","type":"change","z":"768bceac.aed6e","name":"switch","rules":[{"t":"set","p":"switchred","pt":"flow","to":"payload","tot":"msg"}],"action":"","property":"","from":"","to":"","reg":false,"x":1029,"y":799,"wires":[[]]},{"id":"30d6588d.13e688","type":"inject","z":"768bceac.aed6e","name":"Fan","topic":"","payload":"1","payloadType":"global","repeat":"1","crontab":"","once":false,"onceDelay":0.1,"x":1270,"y":107,"wires":[["822d86a4.bf99b8"]]},{"id":"e0cb2cca.9669c","type":"debug","z":"768bceac.aed6e","name":"","active":true,"tosidebar":true,"console":false,"tostatus":false,"complete":"payload","targetType":"msg","x":1770,"y":67,"wires":[]},{"id":"30c621c2.85b53e","type":"function","z":"768bceac.aed6e","name":"Counter","func":"var COUNT='count';\n\n// initialise the counter to 0 if it doesn't exist already\nvar count = flow.get(COUNT)||0;\ncount += 1;\n// store the value back\nflow.set(COUNT,count);\n// make it part of the outgoing msg object\nmsg.count = count;\nmsg.payload = {} ;\n\nmsg.payload.countFan = count;\n\nnode.log(\"Received particles : \" + count);\n\nreturn msg;","outputs":1,"noerr":0,"x":1610,"y":107,"wires":[["1c89c889.42f367"]]},{"id":"822d86a4.bf99b8","type":"switch","z":"768bceac.aed6e","name":"Change","property":"switchfan","propertyType":"flow","rules":[{"t":"eq","v":"1","vt":"num"}],"checkall":"false","repair":false,"outputs":1,"x":1440,"y":107,"wires":[["30c621c2.85b53e"]]},{"id":"da8bdcd0.e5b9e","type":"function","z":"768bceac.aed6e","name":"reset","func":"var COUNT='count';\n\n// initialise the counter to 0 if it doesn't exist already\nvar count = flow.get(COUNT)||0;\n\nmsg.count = count;\nmsg.payload = {};\nmsg.payload.ppm = count;\n\nnode.log(\"Reset counter at \" + count);\n\n// make it part of the outgoing msg object\ncount = 0;\n\n// store the value back\nflow.set(COUNT,count);\n\nreturn msg;","outputs":1,"noerr":0,"x":1610,"y":67,"wires":[["e0cb2cca.9669c"]]},{"id":"1c89c889.42f367","type":"function","z":"768bceac.aed6e","name":"Watt.sec","func":"msg.payload = parseFloat(msg.payload.countFan *= 0.5.toFixed(1))\nreturn msg;","outputs":1,"noerr":0,"x":1780,"y":107,"wires":[["1b002403.00810c","d00b00cc.c7527","1797ec0d.f0bb44"]]},{"id":"d9a0598.234b8a8","type":"inject","z":"768bceac.aed6e","name":"","topic":"","payload":"","payloadType":"date","repeat":"","crontab":"","once":false,"onceDelay":0.1,"x":1440,"y":67,"wires":[["da8bdcd0.e5b9e"]]},{"id":"1797ec0d.f0bb44","type":"debug","z":"768bceac.aed6e","name":"","active":true,"tosidebar":true,"console":false,"tostatus":false,"complete":"payload","targetType":"msg","x":1950,"y":107,"wires":[]},{"id":"1b002403.00810c","type":"ui_chart","z":"768bceac.aed6e","name":"Fan","group":"4f89b91a.3eb508","order":1,"width":0,"height":0,"label":"Fan_Consumption W.Sec","chartType":"line","legend":"false","xformat":"auto","interpolate":"linear","nodata":"W.Sec","dot":true,"ymin":"","ymax":"","removeOlder":1,"removeOlderPoints":"","removeOlderUnit":"60","cutout":0,"useOneColor":false,"colors":["#131516","#aec7e8","#ff7f0e","#2ca02c","#98df8a","#d62728","#ff9896","#9467bd","#c5b0d5"],"useOldStyle":false,"outputs":1,"x":1950,"y":67,"wires":[[]]},{"id":"aad8f34c.f3a12","type":"inject","z":"768bceac.aed6e","name":"Ext. Fan","topic":"","payload":"1","payloadType":"global","repeat":"1","crontab":"","once":false,"onceDelay":0.1,"x":1280,"y":220,"wires":[["d358adb9.b3323"]]},{"id":"85640e69.f39fb","type":"debug","z":"768bceac.aed6e","name":"","active":true,"tosidebar":true,"console":false,"tostatus":false,"complete":"payload","targetType":"msg","x":1770,"y":180,"wires":[]},{"id":"8affe14a.fb174","type":"function","z":"768bceac.aed6e","name":"Counter","func":"var COUNT='count';\n\n// initialise the counter to 0 if it doesn't exist already\nvar count = flow.get(COUNT)||0;\ncount += 1;\n// store the value back\nflow.set(COUNT,count);\n// make it part of the outgoing msg object\nmsg.count = count;\nmsg.payload = {} ;\n\nmsg.payload.countExhaustFan = count;\n\nnode.log(\"Received particles : \" + count);\n\nreturn msg;","outputs":1,"noerr":0,"x":1610,"y":220,"wires":[["d6624ce6.e738b"]]},{"id":"d358adb9.b3323","type":"switch","z":"768bceac.aed6e","name":"Change","property":"switchexhaustfan","propertyType":"flow","rules":[{"t":"eq","v":"1","vt":"num"}],"checkall":"false","repair":false,"outputs":1,"x":1440,"y":220,"wires":[["8affe14a.fb174"]]},{"id":"d6624ce6.e738b","type":"function","z":"768bceac.aed6e","name":"Watt.sec","func":"msg.payload = parseFloat(msg.payload.countExhaustFan *= 0.5.toFixed(1))\nreturn msg;","outputs":1,"noerr":0,"x":1780,"y":220,"wires":[["e2f9ccd0.faaa9","e3efc4dc.edc5f8","b53f80ba.35879"]]},{"id":"b53f80ba.35879","type":"debug","z":"768bceac.aed6e","name":"","active":true,"tosidebar":true,"console":false,"tostatus":false,"complete":"payload","targetType":"msg","x":1950,"y":220,"wires":[]},{"id":"e2f9ccd0.faaa9","type":"ui_chart","z":"768bceac.aed6e","name":"Exhaust_Fan","group":"894d4af7.4495b8","order":0,"width":0,"height":0,"label":"Exhaust_Fan_Consumption W.Sec","chartType":"line","legend":"false","xformat":"auto","interpolate":"linear","nodata":"W.Sec","dot":true,"ymin":"","ymax":"","removeOlder":1,"removeOlderPoints":"","removeOlderUnit":"60","cutout":0,"useOneColor":false,"colors":["#161717","#aec7e8","#ff7f0e","#2ca02c","#98df8a","#d62728","#ff9896","#9467bd","#c5b0d5"],"useOldStyle":false,"outputs":1,"x":1970,"y":180,"wires":[[]]},{"id":"c9d2433c.5e76d","type":"inject","z":"768bceac.aed6e","name":"Blue Lit","topic":"","payload":"1","payloadType":"global","repeat":"1","crontab":"","once":false,"onceDelay":0.1,"x":1280,"y":380,"wires":[["b0020649.aefb78"]]},{"id":"bd83642.db7fd98","type":"debug","z":"768bceac.aed6e","name":"","active":true,"tosidebar":true,"console":false,"tostatus":false,"complete":"payload","targetType":"msg","x":1770,"y":340,"wires":[]},{"id":"9f7504bb.5eac78","type":"function","z":"768bceac.aed6e","name":"Counter","func":"var COUNT='count';\n\n// initialise the counter to 0 if it doesn't exist already\nvar count = flow.get(COUNT)||0;\ncount += 1;\n// store the value back\nflow.set(COUNT,count);\n// make it part of the outgoing msg object\nmsg.count = count;\nmsg.payload = {} ;\n\nmsg.payload.countBlue = count;\n\nnode.log(\"Received particles : \" + count);\n\nreturn msg;","outputs":1,"noerr":0,"x":1610,"y":380,"wires":[["dfc06825.5b9488"]]},{"id":"b0020649.aefb78","type":"switch","z":"768bceac.aed6e","name":"Change","property":"switchblue","propertyType":"flow","rules":[{"t":"eq","v":"1","vt":"num"}],"checkall":"false","repair":false,"outputs":1,"x":1440,"y":380,"wires":[["9f7504bb.5eac78"]]},{"id":"dfc06825.5b9488","type":"function","z":"768bceac.aed6e","name":"Watt.sec","func":"msg.payload = parseFloat(msg.payload.countBlue *= 0.1.toFixed(1))\nreturn msg;","outputs":1,"noerr":0,"x":1780,"y":380,"wires":[["daf78e5e.d35bd","69d1b933.242248","e66427ab.1b90b8"]]},{"id":"daf78e5e.d35bd","type":"debug","z":"768bceac.aed6e","name":"","active":true,"tosidebar":true,"console":false,"tostatus":false,"complete":"payload","targetType":"msg","x":1950,"y":380,"wires":[]},{"id":"69d1b933.242248","type":"ui_chart","z":"768bceac.aed6e","name":"Blue_Light","group":"4f89b91a.3eb508","order":0,"width":0,"height":0,"label":"Blue_Light_Consumption W.Sec","chartType":"line","legend":"false","xformat":"auto","interpolate":"linear","nodata":"W.Sec","dot":true,"ymin":"","ymax":"","removeOlder":1,"removeOlderPoints":"","removeOlderUnit":"60","cutout":0,"useOneColor":false,"colors":["#1f77b4","#aec7e8","#ff7f0e","#2ca02c","#98df8a","#d62728","#ff9896","#9467bd","#c5b0d5"],"useOldStyle":false,"outputs":1,"x":1970,"y":340,"wires":[[]]},{"id":"2699332c.58225c","type":"inject","z":"768bceac.aed6e","name":"Main Lit","topic":"","payload":"1","payloadType":"global","repeat":"1","crontab":"","once":false,"onceDelay":0.1,"x":1280,"y":482,"wires":[["45d615de.af168c"]]},{"id":"c0ea411f.84ef1","type":"debug","z":"768bceac.aed6e","name":"","active":true,"tosidebar":true,"console":false,"tostatus":false,"complete":"payload","targetType":"msg","x":1770,"y":442,"wires":[]},{"id":"6bc6771b.ff25c8","type":"function","z":"768bceac.aed6e","name":"Counter","func":"var COUNT='count';\n\n// initialise the counter to 0 if it doesn't exist already\nvar count = flow.get(COUNT)||0;\ncount += 1;\n// store the value back\nflow.set(COUNT,count);\n// make it part of the outgoing msg object\nmsg.count = count;\nmsg.payload = {} ;\n\nmsg.payload.countMain = count;\n\nnode.log(\"Received particles : \" + count);\n\nreturn msg;","outputs":1,"noerr":0,"x":1610,"y":482,"wires":[["c96a8da6.d340a"]]},{"id":"45d615de.af168c","type":"switch","z":"768bceac.aed6e","name":"Change","property":"switchmain","propertyType":"flow","rules":[{"t":"eq","v":"1","vt":"num"}],"checkall":"false","repair":false,"outputs":1,"x":1440,"y":482,"wires":[["6bc6771b.ff25c8"]]},{"id":"c96a8da6.d340a","type":"function","z":"768bceac.aed6e","name":"Watt.sec","func":"msg.payload = parseFloat(msg.payload.countMain *= 0.2.toFixed(1))\nreturn msg;","outputs":1,"noerr":0,"x":1780,"y":482,"wires":[["1877d162.d76b0f","edf8b128.dd522","873fa705.e14d68"]]},{"id":"1877d162.d76b0f","type":"debug","z":"768bceac.aed6e","name":"","active":true,"tosidebar":true,"console":false,"tostatus":false,"complete":"payload","targetType":"msg","x":1950,"y":482,"wires":[]},{"id":"edf8b128.dd522","type":"ui_chart","z":"768bceac.aed6e","name":"Main_Light","group":"457502f7.ad5ebc","order":0,"width":0,"height":0,"label":"Main_Light_Consumption W.Sec","chartType":"line","legend":"false","xformat":"auto","interpolate":"linear","nodata":"W.Sec","dot":true,"ymin":"","ymax":"","removeOlder":1,"removeOlderPoints":"","removeOlderUnit":"60","cutout":0,"useOneColor":false,"colors":["#c20fe6","#aec7e8","#ff7f0e","#2ca02c","#98df8a","#d62728","#ff9896","#9467bd","#c5b0d5"],"useOldStyle":false,"outputs":1,"x":1970,"y":442,"wires":[[]]},{"id":"846f5fc.8b979a","type":"inject","z":"768bceac.aed6e","name":"Orng Lit","topic":"","payload":"1","payloadType":"global","repeat":"1","crontab":"","once":false,"onceDelay":0.1,"x":1280,"y":576,"wires":[["e036e7b8.eafee8"]]},{"id":"67e2a105.514b7","type":"debug","z":"768bceac.aed6e","name":"","active":true,"tosidebar":true,"console":false,"tostatus":false,"complete":"payload","targetType":"msg","x":1770,"y":536,"wires":[]},{"id":"5bb1c268.cf90ec","type":"function","z":"768bceac.aed6e","name":"Counter","func":"var COUNT='count';\n\n// initialise the counter to 0 if it doesn't exist already\nvar count = flow.get(COUNT)||0;\ncount += 1;\n// store the value back\nflow.set(COUNT,count);\n// make it part of the outgoing msg object\nmsg.count = count;\nmsg.payload = {} ;\n\nmsg.payload.countOrange = count;\n\nnode.log(\"Received particles : \" + count);\n\nreturn msg;","outputs":1,"noerr":0,"x":1610,"y":576,"wires":[["4eabf396.7a5b5c"]]},{"id":"e036e7b8.eafee8","type":"switch","z":"768bceac.aed6e","name":"Change","property":"switchorange","propertyType":"flow","rules":[{"t":"eq","v":"1","vt":"num"}],"checkall":"false","repair":false,"outputs":1,"x":1440,"y":576,"wires":[["5bb1c268.cf90ec"]]},{"id":"4eabf396.7a5b5c","type":"function","z":"768bceac.aed6e","name":"Watt.sec","func":"msg.payload = parseFloat(msg.payload.countOrange *= 0.1.toFixed(1))\nreturn msg;","outputs":1,"noerr":0,"x":1780,"y":576,"wires":[["e2533e37.7a395","bbd7abdd.e8b928","3063f0a3.401d1"]]},{"id":"e2533e37.7a395","type":"debug","z":"768bceac.aed6e","name":"","active":true,"tosidebar":true,"console":false,"tostatus":false,"complete":"payload","targetType":"msg","x":1950,"y":576,"wires":[]},{"id":"bbd7abdd.e8b928","type":"ui_chart","z":"768bceac.aed6e","name":"Orange_Light","group":"894d4af7.4495b8","order":1,"width":0,"height":0,"label":"Orange_Light_Consumption W.Sec","chartType":"line","legend":"false","xformat":"auto","interpolate":"linear","nodata":"W.Sec","dot":true,"ymin":"","ymax":"","removeOlder":1,"removeOlderPoints":"","removeOlderUnit":"60","cutout":0,"useOneColor":false,"colors":["#e17f0e","#aec7e8","#ff7f0e","#2ca02c","#98df8a","#d62728","#ff9896","#9467bd","#c5b0d5"],"useOldStyle":false,"outputs":1,"x":1980,"y":536,"wires":[[]]},{"id":"bde843c9.1c0d5","type":"inject","z":"768bceac.aed6e","name":"Gren Lit","topic":"","payload":"1","payloadType":"global","repeat":"1","crontab":"","once":false,"onceDelay":0.1,"x":1280,"y":669,"wires":[["208f75b0.f3ec2a"]]},{"id":"4499d886.07cd68","type":"debug","z":"768bceac.aed6e","name":"","active":true,"tosidebar":true,"console":false,"tostatus":false,"complete":"payload","targetType":"msg","x":1770,"y":629,"wires":[]},{"id":"bc1cec8b.1df9e","type":"function","z":"768bceac.aed6e","name":"Counter","func":"var COUNT='count';\n\n// initialise the counter to 0 if it doesn't exist already\nvar count = flow.get(COUNT)||0;\ncount += 1;\n// store the value back\nflow.set(COUNT,count);\n// make it part of the outgoing msg object\nmsg.count = count;\nmsg.payload = {} ;\n\nmsg.payload.countGreen = count;\n\nnode.log(\"Received particles : \" + count);\n\nreturn msg;","outputs":1,"noerr":0,"x":1610,"y":669,"wires":[["f7afdb27.626a88"]]},{"id":"208f75b0.f3ec2a","type":"switch","z":"768bceac.aed6e","name":"Change","property":"switchgreen","propertyType":"flow","rules":[{"t":"eq","v":"1","vt":"num"}],"checkall":"false","repair":false,"outputs":1,"x":1440,"y":669,"wires":[["bc1cec8b.1df9e"]]},{"id":"f7afdb27.626a88","type":"function","z":"768bceac.aed6e","name":"Watt.sec","func":"msg.payload = parseFloat(msg.payload.countGreen *= 0.1.toFixed(1))\nreturn msg;","outputs":1,"noerr":0,"x":1780,"y":669,"wires":[["a206168f.a59e58","7b22b596.e20a2c","1849b55f.1328fb"]]},{"id":"a206168f.a59e58","type":"debug","z":"768bceac.aed6e","name":"","active":true,"tosidebar":true,"console":false,"tostatus":false,"complete":"payload","targetType":"msg","x":1950,"y":669,"wires":[]},{"id":"7b22b596.e20a2c","type":"ui_chart","z":"768bceac.aed6e","name":"Green_light","group":"1c2d0279.f0649e","order":1,"width":0,"height":0,"label":"Green_Light_Consumption W.Sec","chartType":"line","legend":"false","xformat":"auto","interpolate":"linear","nodata":"W.Sec","dot":true,"ymin":"","ymax":"","removeOlder":1,"removeOlderPoints":"","removeOlderUnit":"60","cutout":0,"useOneColor":false,"colors":["#2ca02c","#aec7e8","#ff7f0e","#2ca02c","#98df8a","#d62728","#ff9896","#9467bd","#c5b0d5"],"useOldStyle":false,"outputs":1,"x":1970,"y":629,"wires":[[]]},{"id":"d8ddf804.199128","type":"inject","z":"768bceac.aed6e","name":"Door Lit","topic":"","payload":"1","payloadType":"global","repeat":"1","crontab":"","once":false,"onceDelay":0.1,"x":1280,"y":758,"wires":[["f58218a7.3ac9f8"]]},{"id":"7ec795ba.f24c2c","type":"function","z":"768bceac.aed6e","name":"Counter","func":"var COUNT='count';\n\n// initialise the counter to 0 if it doesn't exist already\nvar count = flow.get(COUNT)||0;\ncount += 1;\n// store the value back\nflow.set(COUNT,count);\n// make it part of the outgoing msg object\nmsg.count = count;\nmsg.payload = {} ;\n\nmsg.payload.countDoor = count;\n\nnode.log(\"Received particles : \" + count);\n\nreturn msg;","outputs":1,"noerr":0,"x":1610,"y":758,"wires":[["edda44cd.513e48"]]},{"id":"f58218a7.3ac9f8","type":"switch","z":"768bceac.aed6e","name":"Change","property":"switchdoor","propertyType":"flow","rules":[{"t":"eq","v":"1","vt":"num"}],"checkall":"false","repair":false,"outputs":1,"x":1440,"y":758,"wires":[["7ec795ba.f24c2c"]]},{"id":"edda44cd.513e48","type":"function","z":"768bceac.aed6e","name":"Watt.sec","func":"msg.payload = parseFloat(msg.payload.countDoor *= 0.1.toFixed(1))\nreturn msg;","outputs":1,"noerr":0,"x":1780,"y":758,"wires":[["e1efadf3.8e0b6","ebccad42.f177d","8bc4a548.5224a8"]]},{"id":"e1efadf3.8e0b6","type":"debug","z":"768bceac.aed6e","name":"","active":true,"tosidebar":true,"console":false,"tostatus":false,"complete":"payload","targetType":"msg","x":1950,"y":758,"wires":[]},{"id":"261fec55.2de6a4","type":"inject","z":"768bceac.aed6e","name":"Red Lit","topic":"","payload":"1","payloadType":"global","repeat":"1","crontab":"","once":false,"onceDelay":0.1,"x":1280,"y":851,"wires":[["1dd9e9d0.7435b6"]]},{"id":"9f1d34b2.3b1088","type":"debug","z":"768bceac.aed6e","name":"","active":true,"tosidebar":true,"console":false,"tostatus":false,"complete":"payload","targetType":"msg","x":1770,"y":811,"wires":[]},{"id":"650da7b8.b93a48","type":"function","z":"768bceac.aed6e","name":"Counter","func":"var COUNT='count';\n\n// initialise the counter to 0 if it doesn't exist already\nvar count = flow.get(COUNT)||0;\ncount += 1;\n// store the value back\nflow.set(COUNT,count);\n// make it part of the outgoing msg object\nmsg.count = count;\nmsg.payload = {} ;\n\nmsg.payload.countRed = count;\n\nnode.log(\"Received particles : \" + count);\n\nreturn msg;","outputs":1,"noerr":0,"x":1610,"y":851,"wires":[["7da5f4a0.e0d9dc"]]},{"id":"1dd9e9d0.7435b6","type":"switch","z":"768bceac.aed6e","name":"Change","property":"switchred","propertyType":"flow","rules":[{"t":"eq","v":"1","vt":"num"}],"checkall":"false","repair":false,"outputs":1,"x":1440,"y":851,"wires":[["650da7b8.b93a48"]]},{"id":"7da5f4a0.e0d9dc","type":"function","z":"768bceac.aed6e","name":"Watt.sec","func":"msg.payload = parseFloat(msg.payload.countRed *= 0.1.toFixed(1))\nreturn msg;","outputs":1,"noerr":0,"x":1780,"y":851,"wires":[["c13a1cd1.736e6","8834713a.8eeab","75843fcc.9d482"]]},{"id":"c13a1cd1.736e6","type":"debug","z":"768bceac.aed6e","name":"","active":true,"tosidebar":true,"console":false,"tostatus":false,"complete":"payload","targetType":"msg","x":1950,"y":851,"wires":[]},{"id":"8834713a.8eeab","type":"ui_chart","z":"768bceac.aed6e","name":"Red_light","group":"4f89b91a.3eb508","order":2,"width":0,"height":0,"label":"Red_Light_Consumption W.Sec","chartType":"line","legend":"false","xformat":"auto","interpolate":"linear","nodata":"KWS","dot":true,"ymin":"","ymax":"","removeOlder":1,"removeOlderPoints":"","removeOlderUnit":"60","cutout":0,"useOneColor":false,"colors":["#cc2728","#aec7e8","#ff7f0e","#2ca02c","#98df8a","#d62728","#ff9896","#9467bd","#c5b0d5"],"useOldStyle":false,"outputs":1,"x":1960,"y":811,"wires":[[]]},{"id":"d4854f3b.41879","type":"debug","z":"768bceac.aed6e","name":"","active":true,"tosidebar":true,"console":false,"tostatus":false,"complete":"payload","targetType":"msg","x":1770,"y":720,"wires":[]},{"id":"ebccad42.f177d","type":"ui_chart","z":"768bceac.aed6e","name":"Door_light","group":"457502f7.ad5ebc","order":1,"width":0,"height":0,"label":"Door_Light_Consumption W.Sec","chartType":"line","legend":"false","xformat":"auto","interpolate":"linear","nodata":"W.Sec","dot":true,"ymin":"","ymax":"","removeOlder":1,"removeOlderPoints":"","removeOlderUnit":"60","cutout":0,"useOneColor":false,"colors":["#b8b5ba","#aec7e8","#ff7f0e","#2ca02c","#98df8a","#d62728","#ff9896","#9467bd","#c5b0d5"],"useOldStyle":false,"outputs":1,"x":1970,"y":720,"wires":[[]]},{"id":"5d8c5804.6da888","type":"ui_switch","z":"768bceac.aed6e","name":"","label":"Red_Light","tooltip":"","group":"1561bc9b.e559d3","order":1,"width":0,"height":0,"passthru":true,"decouple":"false","topic":"","style":"","onvalue":"1","onvalueType":"num","onicon":"","oncolor":"","offvalue":"0","offvalueType":"num","officon":"","offcolor":"","x":896,"y":836,"wires":[["9d6112c5.d554f","b526accf.0b9e9"]]},{"id":"d00b00cc.c7527","type":"link out","z":"768bceac.aed6e","name":"","links":["b604031b.30743"],"x":1855,"y":132,"wires":[]},{"id":"e3efc4dc.edc5f8","type":"link out","z":"768bceac.aed6e","name":"","links":["b604031b.30743"],"x":1852,"y":248,"wires":[]},{"id":"e66427ab.1b90b8","type":"link out","z":"768bceac.aed6e","name":"","links":["b604031b.30743"],"x":1855,"y":400,"wires":[]},{"id":"873fa705.e14d68","type":"link out","z":"768bceac.aed6e","name":"","links":["b604031b.30743"],"x":1852,"y":500,"wires":[]},{"id":"3063f0a3.401d1","type":"link out","z":"768bceac.aed6e","name":"","links":["b604031b.30743"],"x":1850,"y":594,"wires":[]},{"id":"1849b55f.1328fb","type":"link out","z":"768bceac.aed6e","name":"","links":["b604031b.30743"],"x":1856,"y":687,"wires":[]},{"id":"8bc4a548.5224a8","type":"link out","z":"768bceac.aed6e","name":"","links":["b604031b.30743"],"x":1855,"y":780,"wires":[]},{"id":"75843fcc.9d482","type":"link out","z":"768bceac.aed6e","name":"","links":["b604031b.30743"],"x":1855,"y":880,"wires":[]},{"id":"4ef31d62.18fe84","type":"function","z":"768bceac.aed6e","name":"Sum","func":"msg.payload = msg.payload + msg.payload + msg.payload + msg.payload + msg.payload + msg.payload + msg.payload + msg.payload \nreturn msg;","outputs":1,"noerr":0,"x":2130,"y":420,"wires":[["b10ca345.62c18","650fa56.39bd95c"]]},{"id":"b604031b.30743","type":"link in","z":"768bceac.aed6e","name":"","links":["e3efc4dc.edc5f8","d00b00cc.c7527","8bc4a548.5224a8","3063f0a3.401d1","1849b55f.1328fb","873fa705.e14d68","75843fcc.9d482","e66427ab.1b90b8"],"x":2095,"y":380,"wires":[["4ef31d62.18fe84"]]},{"id":"b10ca345.62c18","type":"ui_chart","z":"768bceac.aed6e","name":"Sum Graph","group":"b836ffe3.92b32","order":0,"width":0,"height":0,"label":"Watt.Sec","chartType":"line","legend":"false","xformat":"auto","interpolate":"linear","nodata":"W.Sec","dot":true,"ymin":"","ymax":"","removeOlder":1,"removeOlderPoints":"","removeOlderUnit":"60","cutout":0,"useOneColor":false,"colors":["#a1bf9b","#aec7e8","#ff7f0e","#2ca02c","#98df8a","#d62728","#ff9896","#9467bd","#c5b0d5"],"useOldStyle":false,"outputs":1,"x":2170,"y":500,"wires":[[]]},{"id":"650fa56.39bd95c","type":"debug","z":"768bceac.aed6e","name":"Sum","active":true,"tosidebar":true,"console":false,"tostatus":false,"complete":"payload","targetType":"msg","x":2260,"y":400,"wires":[]},{"id":"b45736fe.4c2c78","type":"link out","z":"768bceac.aed6e","name":"","links":["351eece8.dded54","64bbf1f4.cb001"],"x":395,"y":200,"wires":[]},{"id":"8e632bf3.18f308","type":"link out","z":"768bceac.aed6e","name":"","links":["351eece8.dded54","64bbf1f4.cb001"],"x":375,"y":320,"wires":[]},{"id":"7bf321d0.f1c82","type":"link out","z":"768bceac.aed6e","name":"","links":["351eece8.dded54","64bbf1f4.cb001"],"x":195,"y":440,"wires":[]},{"id":"351eece8.dded54","type":"link in","z":"768bceac.aed6e","name":"buzzer","links":["8e632bf3.18f308","b45736fe.4c2c78","7bf321d0.f1c82"],"x":495,"y":380,"wires":[["59b40d22.569034"]]},{"id":"64bbf1f4.cb001","type":"link in","z":"768bceac.aed6e","name":"High Alert","links":["8e632bf3.18f308","b45736fe.4c2c78","7bf321d0.f1c82"],"x":455,"y":240,"wires":[["de511404.5ae608"]]},{"id":"4c6fa84f.6831f8","type":"comment","z":"768bceac.aed6e","name":"Electricity Consumption","info":"","x":1300,"y":20,"wires":[]},{"id":"1561bc9b.e559d3","type":"ui_group","z":"","name":"Bedroom","tab":"b5230624.34ddb8","order":2,"disp":true,"width":"6","collapse":false},{"id":"76c72daa.8ac404","type":"ui_group","z":"","name":"Security_Alert","tab":"942e994f.f8f628","order":1,"disp":true,"width":"6","collapse":false},{"id":"7bc51687.4e2538","type":"ui_group","z":"","name":"Kitchen","tab":"b5230624.34ddb8","order":3,"disp":true,"width":"6","collapse":false},{"id":"33731033.34ef4","type":"ui_group","z":"","name":"Temperature","tab":"3eaa423d.21a0de","order":1,"disp":true,"width":"6","collapse":false},{"id":"a5d70956.dca588","type":"ui_group","z":"","name":"Security Activation","tab":"942e994f.f8f628","order":2,"disp":true,"width":"6","collapse":false},{"id":"d554621.98026a","type":"ui_group","z":"","name":"LiveVideo","tab":"827325b.8be65d8","order":1,"disp":false,"width":"8","collapse":false},{"id":"528e8223.243eec","type":"ui_group","z":"","name":"Entrance","tab":"b5230624.34ddb8","order":1,"disp":true,"width":"6","collapse":false},{"id":"a924f6c.a36d908","type":"ui_group","z":"","name":"Balcony","tab":"b5230624.34ddb8","order":4,"disp":true,"width":"6","collapse":false},{"id":"4f89b91a.3eb508","type":"ui_group","z":"","name":"Bedroom","tab":"ede99a21.3405c8","order":3,"disp":true,"width":"6","collapse":false},{"id":"894d4af7.4495b8","type":"ui_group","z":"","name":"Kitchen","tab":"ede99a21.3405c8","order":4,"disp":true,"width":"6","collapse":false},{"id":"457502f7.ad5ebc","type":"ui_group","z":"","name":"Entrance","tab":"ede99a21.3405c8","order":2,"disp":true,"width":"6","collapse":false},{"id":"1c2d0279.f0649e","type":"ui_group","z":"","name":"Balcony","tab":"ede99a21.3405c8","order":5,"disp":true,"width":"6","collapse":false},{"id":"b836ffe3.92b32","type":"ui_group","z":"","name":"Total Electricity Consumption","tab":"ede99a21.3405c8","order":1,"disp":true,"width":"6","collapse":false},{"id":"b5230624.34ddb8","type":"ui_tab","z":"","name":"Smart Home Appliances","icon":"dashboard","order":1,"disabled":false,"hidden":false},{"id":"942e994f.f8f628","type":"ui_tab","z":"","name":"Smart Home Security","icon":"dashboard","order":7,"disabled":false,"hidden":false},{"id":"3eaa423d.21a0de","type":"ui_tab","z":"","name":"Smart Home Environment","icon":"dashboard","order":2,"disabled":false,"hidden":false},{"id":"827325b.8be65d8","type":"ui_tab","z":"","name":"Smart Home Live","icon":"dashboard","order":6,"disabled":false,"hidden":false},{"id":"ede99a21.3405c8","type":"ui_tab","z":"","name":"Electricity Consumption","icon":"dashboard","order":3,"disabled":false,"hidden":false}]